{
  "model_name": "unq-0ef36979eccfba6e376ce5eaed61fb92",
  "device_type": "SM-F926B",
  "os_version": "14 | UP1A.231005.007",
  "valid": true,
  "emulator": false,
  "iterations": 20,
  "duration": 10743500,
  "unit": "NPU",
  "cpu_duration": 47916700,
  "cpu_min_duration": 46893000,
  "cpu_max_duration": 57655000,
  "cpu_std_dev": 3079000.0,
  "gpu_duration": 10757300,
  "gpu_min_duration": 10569000,
  "gpu_max_duration": 17370000,
  "gpu_std_dev": 975000.0,
  "npu_duration": 10743500,
  "npu_min_duration": 10558000,
  "npu_max_duration": 17709000,
  "npu_std_dev": 1027000.0,
  "total_ram_kb": 11631760,
  "free_ram_kb": 2720280,
  "available_ram_kb": 4960668,
  "cached_kb": 4537048,
  "in_dim_0": 1,
  "in_dim_1": 64,
  "in_dim_2": 64,
  "in_dim_3": 3,
  "device_analytics": {
    "timestamp": 1772233711.952429,
    "cpu_info": {
      "cpu_cores": 8,
      "processors": [
        {
          "processor": "0",
          "bogomips": "38.40",
          "features": "fp asimd evtstrm aes pmull sha1 sha2 crc32 atomics fphp asimdhp cpuid asimdrdm lrcpc dcpop asimddp",
          "cpu implementer": "0x41",
          "cpu architecture": "8",
          "cpu variant": "0x2",
          "cpu part": "0xd05",
          "cpu revision": "0"
        },
        {
          "processor": "1",
          "bogomips": "38.40",
          "features": "fp asimd evtstrm aes pmull sha1 sha2 crc32 atomics fphp asimdhp cpuid asimdrdm lrcpc dcpop asimddp",
          "cpu implementer": "0x41",
          "cpu architecture": "8",
          "cpu variant": "0x2",
          "cpu part": "0xd05",
          "cpu revision": "0"
        },
        {
          "processor": "2",
          "bogomips": "38.40",
          "features": "fp asimd evtstrm aes pmull sha1 sha2 crc32 atomics fphp asimdhp cpuid asimdrdm lrcpc dcpop asimddp",
          "cpu implementer": "0x41",
          "cpu architecture": "8",
          "cpu variant": "0x2",
          "cpu part": "0xd05",
          "cpu revision": "0"
        },
        {
          "processor": "3",
          "bogomips": "38.40",
          "features": "fp asimd evtstrm aes pmull sha1 sha2 crc32 atomics fphp asimdhp cpuid asimdrdm lrcpc dcpop asimddp",
          "cpu implementer": "0x41",
          "cpu architecture": "8",
          "cpu variant": "0x2",
          "cpu part": "0xd05",
          "cpu revision": "0"
        }
      ],
      "arm_architecture": {
        "hardware": "SM8350",
        "features": "fp asimd evtstrm aes pmull sha1 sha2 crc32 atomics fphp asimdhp cpuid asimdrdm lrcpc dcpop asimddp",
        "cpu_implementer": "0x41",
        "cpu_architecture": "8",
        "cpu_variant": "0x1",
        "cpu_part": "0xd44",
        "cpu_revision": "0"
      }
    }
  }
}