[
    {
        "accuracy": 0.8254,
        "batch": 32,
        "best_accuracy": 0.8254,
        "best_epoch": 18,
        "cpu_count": 24,
        "cpu_type": "x86_64",
        "cpu_usage_percent": 5.4,
        "duration": 627169527862,
        "epoch_max": 50,
        "gpu_memory_kb": 2821817.5,
        "gpu_memory_usage_percent": 0.1,
        "gpu_total_memory_kb": 24696896.0,
        "gpu_type": "NVIDIA GeForce RTX 4090",
        "gradient_norm": 1.9963371958203473,
        "lr": 0.1465887232360373,
        "lr_now": 0.1465887232360373,
        "momentum": 0.7318332085800009,
        "occupied_gpu_memory_kb": 25872.0,
        "occupied_ram_kb": 15613540.0,
        "ram_usage_percent": 47.9,
        "samples_per_second": 1443.6378089634911,
        "test_loss": 0.8254243703172229,
        "total_ram_kb": 32620620.0,
        "train_accuracy": 0.99096,
        "train_loss": 0.028826794246637238,
        "transform": "bf-v1-CenterCrop_Pad_4",
        "uid": "a15925f109b670a1d90ba3ba7e4afcb5"
    },
    {
        "accuracy": 0.8164,
        "batch": 32,
        "best_accuracy": 0.8264,
        "best_epoch": 11,
        "duration": 666517385850,
        "epoch_max": 50,
        "gpu_memory_kb": 2008442.5,
        "gradient_norm": 2.476361691466493,
        "lr": 0.1465887232360373,
        "lr_now": 0.1465887232360373,
        "momentum": 0.7318332085800009,
        "samples_per_second": 1345.339494854475,
        "test_loss": 0.9150618013625328,
        "train_accuracy": 0.97778,
        "train_loss": 0.06424604859993727,
        "transform": "bf-v1-CenterCrop_Pad_4",
        "uid": "ceaaf8d52b45c90dc0c3826c124b2f74"
    }
]