[
    {
        "accuracy": 0.9873,
        "batch": 64,
        "best_accuracy": 0.9873,
        "best_epoch": 4,
        "dropout": 0.26830476871942177,
        "duration": 388755665126,
        "epoch_max": 5,
        "gpu_memory_kb": 1034790.0,
        "gradient_norm": 2.3524365238243927,
        "lr": 0.0015180480877407451,
        "lr_now": 0.0015180480877407451,
        "momentum": 0.9472647654937703,
        "samples_per_second": 613.719775263905,
        "test_loss": 0.03514298109870547,
        "train_accuracy": 0.99015,
        "train_loss": 0.03310564174886489,
        "transform": "echo_299",
        "uid": "cdb655bf5c723cf799d87261df4209d0"
    },
    {
        "accuracy": 0.9724,
        "batch": 16,
        "best_accuracy": 0.9724,
        "best_epoch": 4,
        "dropout": 0.471208854121667,
        "duration": 223004577985,
        "epoch_max": 5,
        "gpu_memory_kb": 705367.5,
        "gradient_norm": 0.00787798750313626,
        "lr": 0.18197103014195548,
        "lr_now": 0.18197103014195548,
        "momentum": 0.07185673617914956,
        "samples_per_second": 1077.7857019522546,
        "test_loss": 0.09999897104395786,
        "train_accuracy": 0.9715166666666667,
        "train_loss": 0.09099189047147083,
        "transform": "bf-v1-RandomHorizontalFlip_Pad_RandomRotation",
        "uid": "358ef97febe70bba0058b34603c80fec"
    },
    {
        "accuracy": 0.966,
        "batch": 8,
        "best_accuracy": 0.966,
        "best_epoch": 4,
        "dropout": 0.11796368879482355,
        "duration": 266861475456,
        "epoch_max": 5,
        "gpu_memory_kb": 706537.5,
        "gradient_norm": 0.00918835726082319,
        "lr": 0.0029185713455033885,
        "lr_now": 0.0029185713455033885,
        "momentum": 0.6873625762503183,
        "samples_per_second": 900.1319257113805,
        "test_loss": 0.12230632895722504,
        "train_accuracy": 0.96605,
        "train_loss": 0.12600565505880723,
        "transform": "bf-v1-CenterCrop_RandomHorizontalFlip_2",
        "uid": "c732de35c1294ac8c4349e1501306aed"
    },
    {
        "accuracy": 0.9321,
        "batch": 64,
        "best_accuracy": 0.9504,
        "best_epoch": 3,
        "dropout": 0.11517796487984083,
        "duration": 87393615518,
        "epoch_max": 5,
        "gpu_memory_kb": 729411.5,
        "gradient_norm": 2.6721383611178164,
        "lr": 0.7303938108112018,
        "lr_now": 0.7303938108112018,
        "momentum": 0.1845049371008961,
        "samples_per_second": 2760.3971613337094,
        "test_loss": 0.18386376765704934,
        "train_accuracy": 0.93765,
        "train_loss": 0.17717444118477707,
        "transform": "norm_flip",
        "uid": "b904c3a366a728fcc5cc72b1e8f3c997"
    },
    {
        "accuracy": 0.8303,
        "batch": 8,
        "best_accuracy": 0.8609,
        "best_epoch": 3,
        "dropout": 0.16121327929921997,
        "duration": 267985104797,
        "epoch_max": 5,
        "gpu_memory_kb": 707209.5,
        "gradient_norm": 2.999999700165092,
        "lr": 0.18485204110836212,
        "lr_now": 0.18485204110836212,
        "momentum": 0.7613787035942936,
        "samples_per_second": 899.0737738565251,
        "test_loss": 1.6411355436395447,
        "train_accuracy": 0.82225,
        "train_loss": 1.5708940102946973,
        "transform": "bf-v1-RandomHorizontalFlip_CenterCrop_5",
        "uid": "2a9e8078202f5e6235dbf95555d72fd6"
    }
]