[
    {
        "accuracy": 0.8107,
        "batch": 128,
        "best_accuracy": 0.8107,
        "best_epoch": 10,
        "duration": 356952651065,
        "epoch_max": 50,
        "gpu_memory_kb": 2008442.5,
        "gradient_norm": 1.7657078554406684,
        "lr": 0.03854910878825272,
        "lr_now": 0.03854910878825272,
        "momentum": 0.9420473370193635,
        "samples_per_second": 1414.8073868668519,
        "test_loss": 0.5971348738368554,
        "train_accuracy": 0.93408,
        "train_loss": 0.19823576536629817,
        "transform": "bf-v1-RandomPosterize_CenterCrop_4",
        "uid": "b536c98389708973ee420fadd7787847"
    },
    {
        "accuracy": 0.7869,
        "batch": 128,
        "best_accuracy": 0.8098,
        "best_epoch": 8,
        "cpu_count": 24,
        "cpu_type": "x86_64",
        "cpu_usage_percent": 12.3,
        "duration": 335084468678,
        "epoch_max": 50,
        "gpu_memory_kb": 5448892.0,
        "gpu_memory_usage_percent": 0.13,
        "gpu_total_memory_kb": 24696896.0,
        "gpu_type": "NVIDIA GeForce RTX 4090",
        "gradient_norm": 1.2550093597565664,
        "lr": 0.03854910878825272,
        "momentum": 0.9420473370193635,
        "occupied_gpu_memory_kb": 33279.0,
        "occupied_ram_kb": 15884500.0,
        "ram_usage_percent": 48.7,
        "samples_per_second": 1490.368916304191,
        "test_loss": 0.7197855677031264,
        "total_ram_kb": 32620620.0,
        "train_accuracy": 0.8921,
        "train_loss": 0.30220653977997775,
        "transform": "bf-v1-RandomPosterize_CenterCrop_4",
        "uid": "e7932f9753a2810967fd22fc0b955ea6"
    }
]