[
    {
        "accuracy": 0.7975,
        "batch": 64,
        "best_accuracy": 0.8259,
        "best_epoch": 29,
        "cpu_count": 24,
        "cpu_type": "x86_64",
        "cpu_usage_percent": 10.9,
        "duration": 1130290421027,
        "epoch_max": 50,
        "gpu_memory_kb": 7319161.5,
        "gpu_memory_usage_percent": 0.17,
        "gpu_total_memory_kb": 24696896.0,
        "gpu_type": "NVIDIA GeForce RTX 4090",
        "gradient_norm": 2.9519228202100734,
        "lr": 0.19343804115802973,
        "lr_now": 0.19343804115802973,
        "momentum": 0.6068680082293528,
        "occupied_gpu_memory_kb": 41703.0,
        "occupied_ram_kb": 14140916.0,
        "ram_usage_percent": 43.3,
        "samples_per_second": 1327.4146022031618,
        "test_loss": 1.272667064218764,
        "total_ram_kb": 32620620.0,
        "train_accuracy": 0.9722,
        "train_loss": 0.08502250862144985,
        "transform": "bf-v1-Pad_RandomAutocontrast_RandomAdjustSharpnes",
        "uid": "fbc2b25a191bc5848cc9aaf70140343f"
    }
]