[
    {
        "accuracy": 0.8138,
        "batch": 128,
        "best_accuracy": 0.8138,
        "best_epoch": 43,
        "duration": 1082166118080,
        "epoch_max": 50,
        "gpu_memory_kb": 1390184.5,
        "gradient_norm": 0.0017101566050618927,
        "lr": 0.0327621403553034,
        "lr_now": 0.0327621403553034,
        "momentum": 0.9014104003517412,
        "samples_per_second": 2006.090116782765,
        "test_loss": 1.379349349420282,
        "train_accuracy": 1.0,
        "train_loss": 0.00012569531300843544,
        "transform": "bf-v1-CenterCrop_RandomGrayscale_6",
        "uid": "00fb4d38637d0b19d146d5acb85fea33"
    },
    {
        "accuracy": 0.8105,
        "batch": 128,
        "best_accuracy": 0.8128,
        "best_epoch": 42,
        "cpu_count": 24,
        "cpu_type": "x86_64",
        "cpu_usage_percent": 6.7,
        "duration": 988657470441,
        "epoch_max": 50,
        "gpu_memory_kb": 2820921.5,
        "gpu_memory_usage_percent": 0.13,
        "gpu_total_memory_kb": 24696896.0,
        "gpu_type": "NVIDIA GeForce RTX 4090",
        "gradient_norm": 0.005957700786433423,
        "lr": 0.0327621403553034,
        "lr_now": 0.0327621403553034,
        "momentum": 0.9014104003517412,
        "occupied_gpu_memory_kb": 30960.0,
        "occupied_ram_kb": 13463556.0,
        "ram_usage_percent": 41.3,
        "samples_per_second": 2180.001210390736,
        "test_loss": 1.369697029077554,
        "total_ram_kb": 32620620.0,
        "train_accuracy": 0.99998,
        "train_loss": 0.00010145489967728788,
        "transform": "bf-v1-CenterCrop_RandomGrayscale_6",
        "uid": "15f7fa692cf242ad4865ac4ac245ffde"
    }
]