[
    {
        "accuracy": 0.2715923566878981,
        "batch": 4,
        "best_accuracy": 0.2715923566878981,
        "best_epoch": 1,
        "duration": 222079382414,
        "epoch_max": 5,
        "gpu_memory_kb": 98369.5,
        "gradient_norm": 1.9569900863282017,
        "lr": 0.0011947628900276042,
        "lr_now": 0.0011947628900276042,
        "momentum": 0.7700668446731685,
        "samples_per_second": 42.637969811668185,
        "test_loss": 2.0715596091055337,
        "train_accuracy": 0.2836624775583483,
        "train_loss": 2.045421304130876,
        "transform": "bf-v1-RandomRotation_46",
        "uid": "3f1298bf9c41fc578391a901a0770215"
    },
    {
        "accuracy": 0.2397452229299363,
        "batch": 128,
        "best_accuracy": 0.2397452229299363,
        "best_epoch": 1,
        "duration": 211036606321,
        "epoch_max": 5,
        "gpu_memory_kb": 11420094.5,
        "gradient_norm": 0.48946070583757206,
        "lr": 0.850787946631316,
        "lr_now": 0.850787946631316,
        "momentum": 0.6763397848251004,
        "samples_per_second": 44.86905176653747,
        "test_loss": 2.119181186922135,
        "train_accuracy": 0.25525398669342064,
        "train_loss": 2.098508399886054,
        "transform": "bf-v1-Pad_RandomPosterize_CenterCrop",
        "uid": "43c207295039bf55b71862ce07135b99"
    },
    {
        "accuracy": 0.18445859872611464,
        "batch": 64,
        "duration": 43782639836,
        "epoch_max": 1,
        "lr": 0.012907143823113934,
        "momentum": 0.026447508970353417,
        "transform": "bf-v1-RandomAdjustSharpnes_RandomSolarize_2",
        "uid": "d8c2a617f8d9cdd6a18683e2a792d630"
    },
    {
        "accuracy": 0.16535031847133758,
        "batch": 2,
        "best_accuracy": 0.16535031847133758,
        "best_epoch": 1,
        "duration": 269680593674,
        "epoch_max": 5,
        "gpu_memory_kb": 11420094.5,
        "gradient_norm": 1.8386238059204367,
        "lr": 0.00036648115109937535,
        "lr_now": 0.00036648115109937535,
        "momentum": 0.24718135916105266,
        "samples_per_second": 35.111965726496656,
        "test_loss": 2.2434583505197137,
        "train_accuracy": 0.1687612208258528,
        "train_loss": 2.2353278868049857,
        "transform": "bf-v1-RandomAdjustSharpnes",
        "uid": "6f32aecf7d4157668b821f9ccab4bc06"
    }
]