[
    {
        "accuracy": 0.7414,
        "batch": 4,
        "best_accuracy": 0.7414,
        "best_epoch": 3,
        "cpu_count": 24,
        "cpu_type": "x86_64",
        "cpu_usage_percent": 4.2,
        "duration": 295923814639,
        "epoch_max": 50,
        "gpu_memory_kb": 2821817.5,
        "gpu_memory_usage_percent": 0.6,
        "gpu_total_memory_kb": 24696896.0,
        "gpu_type": "NVIDIA GeForce RTX 4090",
        "gradient_norm": 0.9999995967023866,
        "lr": 0.352412941555112,
        "momentum": 0.5012228507415079,
        "occupied_gpu_memory_kb": 149308.5,
        "occupied_ram_kb": 14928740.0,
        "ram_usage_percent": 45.8,
        "samples_per_second": 508.7607428755947,
        "test_loss": 0.8582446464806796,
        "total_ram_kb": 32620620.0,
        "train_accuracy": 0.77858,
        "train_loss": 0.7060505957935012,
        "transform": "bf-v1-Pad_CenterCrop_RandomHorizontalFlip",
        "uid": "723f643e685cc7b2c6ab2092205e68a8"
    },
    {
        "accuracy": 0.728,
        "batch": 4,
        "best_accuracy": 0.728,
        "best_epoch": 3,
        "duration": 294572266524,
        "epoch_max": 50,
        "gpu_memory_kb": 422520.0,
        "gradient_norm": 0.999999431571137,
        "lr": 0.352412941555112,
        "lr_now": 0.352412941555112,
        "momentum": 0.5012228507415079,
        "samples_per_second": 508.53758950005334,
        "test_loss": 0.8675764279065683,
        "train_accuracy": 0.77432,
        "train_loss": 0.6981299545277588,
        "transform": "bf-v1-Pad_CenterCrop_RandomHorizontalFlip",
        "uid": "a2511803d12581279397666e33e0ca77"
    },
    {
        "accuracy": 0.7233,
        "batch": 4,
        "duration": 291797267328,
        "epoch_max": 5,
        "lr": 0.352412941555112,
        "momentum": 0.5012228507415079,
        "transform": "bf-v1-Pad_CenterCrop_RandomHorizontalFlip",
        "uid": "a8dbe83128807ce0d8c9bf35fdf9aeb4"
    },
    {
        "accuracy": 0.6209,
        "batch": 512,
        "duration": 42668695357,
        "epoch_max": 5,
        "lr": 0.13322636510513025,
        "momentum": 0.8503772093792562,
        "transform": "bf-v1-RandomPerspective_RandomPosterize_4",
        "uid": "eada77bdc2676f9ee5e8d50a77944289"
    },
    {
        "accuracy": 0.5698,
        "batch": 16,
        "duration": 73884661589,
        "epoch_max": 5,
        "lr": 0.004424484936998661,
        "momentum": 0.7510446652550347,
        "transform": "norm_flip",
        "uid": "dad6ea82b37e399796bfec6e11997066"
    },
    {
        "accuracy": 0.3839,
        "batch": 16,
        "duration": 84794572701,
        "epoch_max": 5,
        "lr": 0.00027803316595515577,
        "momentum": 0.8859456553107254,
        "transform": "bf-v1-RandomHorizontalFlip_RandomPosterize_4",
        "uid": "21be7c7bd216ff5926dab82f2f7abf39"
    }
]