[
    {
        "accuracy": 0.5036,
        "batch": 64,
        "best_accuracy": 0.5036,
        "best_epoch": 1,
        "cpu_count": 128,
        "cpu_type": "x86_64",
        "cpu_usage_percent": 1.8,
        "dropout": 0.31456708730213545,
        "duration": 21606233675,
        "epoch_max": 1,
        "gpu_memory_kb": 11616434.0,
        "gpu_memory_usage_percent": 9.14,
        "gpu_total_memory_kb": 24734080.0,
        "gpu_type": "NVIDIA GeForce RTX 3090",
        "gradient_norm": 2.999999639819366,
        "lr": 0.01,
        "momentum": 0.9,
        "occupied_gpu_memory_kb": 2259892.5,
        "occupied_ram_kb": 28285980.0,
        "ram_usage_percent": 12.8,
        "samples_per_second": 2314.172828238256,
        "test_loss": 1.3633114183024995,
        "total_ram_kb": 263710532.0,
        "train_accuracy": 0.5075,
        "train_loss": 1.345953206424518,
        "transform": "norm_32",
        "uid": "d219daa8aed1fe87b4f311d8604c84b9"
    }
]