[
    {
        "accuracy": 0.8168023970497849,
        "batch": 8,
        "duration": 271222197987,
        "lr": 0.005060016512149201,
        "momentum": 0.4918421070845501,
        "transform": "norm_32_flip",
        "uid": "a735a8dfcef23780545f290e37a90582"
    },
    {
        "accuracy": 0.2464658881376767,
        "batch": 64,
        "duration": 100963611619,
        "lr": 0.0014247641979568582,
        "momentum": 0.5121969692511759,
        "transform": "norm_128_flip",
        "uid": "8e74616642f82c8247f60a83f36027c1"
    },
    {
        "accuracy": 0.19606637984019668,
        "batch": 16,
        "duration": 609034831495,
        "lr": 0.00014104013826019533,
        "momentum": 0.5560701478018257,
        "transform": "echo_299",
        "uid": "97169385a694ce8ee8b1bbe525d08c4b"
    },
    {
        "accuracy": 0.19595113706207745,
        "batch": 128,
        "duration": 467053388052,
        "lr": 0.0021884961272784277,
        "momentum": 0.3487009850995668,
        "transform": "echo_299_flip",
        "uid": "c90cbcc95160aa62db73abff4c55cdb5"
    },
    {
        "accuracy": 0.1930700676090965,
        "batch": 256,
        "duration": 55597990126,
        "lr": 0.0002774281723482879,
        "momentum": 0.10472320464345353,
        "transform": "norm_64_flip",
        "uid": "35bceb6b077f29817304bcbe75fb9ae5"
    }
]