[
    {
        "accuracy": 0.33819913952059005,
        "batch": 256,
        "best_accuracy": 0.33819913952059005,
        "best_epoch": 3,
        "dropout": 0.3886500297217995,
        "duration": 292103495421,
        "epoch_max": 5,
        "gpu_memory_kb": 1369418.0,
        "gradient_norm": 1.4445277952764621,
        "lr": 0.19520668965676385,
        "lr_now": 0.19520668965676385,
        "momentum": 0.5847022749217087,
        "samples_per_second": 753.5628880522436,
        "test_loss": 1.9004854840390824,
        "train_accuracy": 0.31112385164557654,
        "train_loss": 1.9115971231294426,
        "transform": "bf-v1-RandomPosterize_RandomHorizontalFlip_6",
        "uid": "4274db0dfc973dbb7235b7f3b0495d9d"
    },
    {
        "accuracy": 0.1958743085433313,
        "batch": 4096,
        "best_accuracy": 0.1958743085433313,
        "best_epoch": 1,
        "dropout": 0.39018321378497683,
        "duration": 453248312196,
        "epoch_max": 5,
        "gpu_memory_kb": 6018830.0,
        "gradient_norm": 0.1054882387698308,
        "lr": 0.019829046939738054,
        "lr_now": 0.019829046939738054,
        "momentum": 0.3868054419914523,
        "samples_per_second": 485.37236978324324,
        "test_loss": 2.276212590081351,
        "train_accuracy": 0.18921058738414076,
        "train_loss": 2.2787852419747248,
        "transform": "bf-v1-RandomHorizontalFlip_Pad_RandomRotation",
        "uid": "79c58e22e2d402e7d04be8f876f75147"
    },
    {
        "accuracy": 0.1958743085433313,
        "batch": 128,
        "best_accuracy": 0.1958743085433313,
        "best_epoch": 1,
        "dropout": 0.2019643134972684,
        "duration": 1967193096655,
        "epoch_max": 5,
        "gpu_memory_kb": 6018830.0,
        "gradient_norm": 0.1444151498132695,
        "lr": 0.003220361779856637,
        "lr_now": 0.003220361779856637,
        "momentum": 0.0667647991845256,
        "samples_per_second": 128.5589914560951,
        "test_loss": 2.242188673393399,
        "train_accuracy": 0.18921058738414076,
        "train_loss": 2.2495425180198843,
        "transform": "echo_299_flip",
        "uid": "ce51bd20bba892e57d8f314aff18e045"
    },
    {
        "accuracy": 0.1958743085433313,
        "batch": 512,
        "best_accuracy": 0.1958743085433313,
        "best_epoch": 1,
        "dropout": 0.36563571964899483,
        "duration": 398854856487,
        "epoch_max": 5,
        "gpu_memory_kb": 1369418.0,
        "gradient_norm": 0.1539636093945724,
        "lr": 0.1796089204133666,
        "lr_now": 0.1796089204133666,
        "momentum": 0.36044237540403445,
        "samples_per_second": 547.6301805008071,
        "test_loss": 2.2240617742725446,
        "train_accuracy": 0.18921058738414076,
        "train_loss": 2.235746009482278,
        "transform": "bf-v1-RandomAutocontrast_Pad_4",
        "uid": "bbade4b7e8f3dbedd8616579093725e6"
    }
]