[
    {
        "accuracy": 0.4548,
        "batch": 64,
        "dropout": 0.2,
        "duration": 191024990638,
        "epoch": 1,
        "lr": 0.01,
        "momentum": 0.9,
        "transform": "norm_256_flip",
        "uid": "268985784c034788d34ad31d0305cb7f"
    },
    {
        "accuracy": 0.4383,
        "batch": 256,
        "best_accuracy": 0.4383,
        "best_epoch": 1,
        "duration": 73659399773,
        "epoch_max": 5,
        "gpu_memory_kb": 2820163.0,
        "gradient_norm": 4.3633814342956185,
        "lr": 0.01876648899788364,
        "lr_now": 0.01876648899788364,
        "momentum": 0.9332979376103597,
        "samples_per_second": 678.8087432524086,
        "test_loss": 1.6636552393436432,
        "train_accuracy": 0.44396,
        "train_loss": 1.6305119474323428,
        "transform": "bf-v1-RandomPerspective_RandomAutocontrast_2",
        "uid": "ca8b6a2b7cb467a3511ec3a136349ab6"
    },
    {
        "accuracy": 0.4023,
        "batch": 4,
        "best_accuracy": 0.4023,
        "best_epoch": 1,
        "duration": 266841475038,
        "epoch_max": 5,
        "gpu_memory_kb": 2820163.0,
        "gradient_norm": 40.882501684211455,
        "lr": 0.0005219141144175251,
        "lr_now": 0.0005219141144175251,
        "momentum": 0.4688886690906374,
        "samples_per_second": 187.37785321792563,
        "test_loss": 1.6364779893755912,
        "train_accuracy": 0.39492,
        "train_loss": 1.6456746129703521,
        "transform": "bf-v1-RandomCrop_CenterCrop_RandomAutocontrast",
        "uid": "74c7f2a8fdd28e56ce89cbed0574be13"
    },
    {
        "accuracy": 0.1592,
        "batch": 16,
        "best_accuracy": 0.1592,
        "best_epoch": 1,
        "duration": 131504011175,
        "epoch_max": 5,
        "gpu_memory_kb": 2820163.0,
        "gradient_norm": 8.710225380686689,
        "lr": 1.7689686332523627e-05,
        "lr_now": 1.7689686332523627e-05,
        "momentum": 0.7228507596242518,
        "samples_per_second": 380.2193091786295,
        "test_loss": 2.2573759994506837,
        "train_accuracy": 0.15676,
        "train_loss": 2.259776399383545,
        "transform": "norm_128_flip",
        "uid": "7dbcf1e200f1b466de933fe87ed863fe"
    },
    {
        "accuracy": 0.1469,
        "batch": 16,
        "best_accuracy": 0.1469,
        "best_epoch": 1,
        "duration": 99827446349,
        "epoch_max": 5,
        "gpu_memory_kb": 2820163.0,
        "gradient_norm": 13.73669828813785,
        "lr": 3.597638752932479e-05,
        "lr_now": 3.597638752932479e-05,
        "momentum": 0.07740253825773791,
        "samples_per_second": 500.869114287872,
        "test_loss": 2.273278762435913,
        "train_accuracy": 0.14684,
        "train_loss": 2.272446318435669,
        "transform": "bf-v1-RandomGrayscale_Grayscale_2",
        "uid": "ac6a517dba6a82f5295c00e49d79e51a"
    }
]