[
    {
        "accuracy": 0.3796,
        "batch": 32,
        "best_accuracy": 0.3796,
        "best_epoch": 3,
        "dropout": 0.14587186822046805,
        "duration": 506345639932,
        "epoch_max": 5,
        "gpu_memory_kb": 961276.5,
        "gradient_norm": 2.999999446719488,
        "lr": 0.14464428077967845,
        "lr_now": 0.14464428077967845,
        "momentum": 0.3106740716383034,
        "samples_per_second": 297.03212783295123,
        "test_loss": 2.4202625602959826,
        "train_accuracy": 0.42708,
        "train_loss": 2.158423425063672,
        "transform": "bf-v1-RandomHorizontalFlip_RandomAutocontrast_RandomAdjustSharpnes_256",
        "uid": "1ad91496b743f407636334a76a9932ac"
    },
    {
        "accuracy": 0.2615,
        "batch": 32,
        "best_accuracy": 0.2615,
        "best_epoch": 3,
        "dropout": 0.23002023583586906,
        "duration": 114221257241,
        "epoch_max": 5,
        "gpu_memory_kb": 598022.0,
        "gradient_norm": 2.999999522292926,
        "lr": 0.030316653656465836,
        "lr_now": 0.030316653656465836,
        "momentum": 0.8590266036931354,
        "samples_per_second": 1327.657380190994,
        "test_loss": 3.0382472250027397,
        "train_accuracy": 0.28574,
        "train_loss": 2.853778265945742,
        "transform": "bf-v1-RandomEqualize_RandomAutocontrast_2",
        "uid": "bb369389b3f7ec48a0143c954cf54dbd"
    },
    {
        "accuracy": 0.2353,
        "batch": 8,
        "best_accuracy": 0.2353,
        "best_epoch": 3,
        "dropout": 0.053300257545992324,
        "duration": 172291447541,
        "epoch_max": 5,
        "gpu_memory_kb": 582973.5,
        "gradient_norm": 2.9999998801317207,
        "lr": 0.012152192469939531,
        "lr_now": 0.012152192469939531,
        "momentum": 0.3953637344678079,
        "samples_per_second": 871.1503293055928,
        "test_loss": 3.1511831068992615,
        "train_accuracy": 0.24208,
        "train_loss": 3.0394085841560363,
        "transform": "bf-v1-CenterCrop_RandomAdjustSharpnes_RandomPosterize",
        "uid": "e18607835de5161d04d95a9adfb32e8a"
    },
    {
        "accuracy": 0.0153,
        "batch": 32,
        "best_accuracy": 0.02,
        "best_epoch": 2,
        "dropout": 0.21748548507854343,
        "duration": 105641783888,
        "epoch_max": 5,
        "gpu_memory_kb": 10201694.0,
        "gradient_norm": 0.4533955200641155,
        "lr": 0.0014583566108433697,
        "lr_now": 0.0014583566108433697,
        "momentum": 0.7924423909010848,
        "samples_per_second": 1424.3505336754613,
        "test_loss": 4.6012693106556855,
        "train_accuracy": 0.0145,
        "train_loss": 4.6011975090700465,
        "transform": "bf-v1-CenterCrop_RandomPosterize_RandomRotation",
        "uid": "1b3ccedcf97ef8540c1963edd8ed700a"
    }
]