[
    {
        "accuracy": 0.8719,
        "batch": 8,
        "best_accuracy": 0.8719,
        "best_epoch": 14,
        "cpu_count": 24,
        "cpu_type": "x86_64",
        "cpu_usage_percent": 6.9,
        "duration": 779588135792,
        "epoch_max": 50,
        "gpu_memory_kb": 2821817.5,
        "gpu_memory_usage_percent": 0.12,
        "gpu_total_memory_kb": 24696896.0,
        "gpu_type": "NVIDIA GeForce RTX 4090",
        "gradient_norm": 2.10297449398047,
        "lr": 0.05872698538021697,
        "lr_now": 0.05872698538021697,
        "momentum": 0.9160530704698054,
        "occupied_gpu_memory_kb": 30430.5,
        "occupied_ram_kb": 14949580.0,
        "ram_usage_percent": 45.8,
        "samples_per_second": 888.6491439094367,
        "test_loss": 0.3994725348390173,
        "total_ram_kb": 32620620.0,
        "train_accuracy": 0.9356,
        "train_loss": 0.19117006072278134,
        "transform": "bf-v1-RandomHorizontalFlip_RandomCrop_RandomPosterize",
        "uid": "56eb7cda7dceebf8712bc9a5cff015d8"
    },
    {
        "accuracy": 0.8527,
        "batch": 8,
        "best_accuracy": 0.8549,
        "best_epoch": 13,
        "duration": 795643033256,
        "epoch_max": 50,
        "gpu_memory_kb": 422520.0,
        "gradient_norm": 1.3390466444440354,
        "lr": 0.05872698538021697,
        "lr_now": 0.05872698538021697,
        "momentum": 0.9160530704698054,
        "samples_per_second": 888.7400013495283,
        "test_loss": 0.4769808321454562,
        "train_accuracy": 0.91176,
        "train_loss": 0.2570693818429252,
        "transform": "bf-v1-RandomHorizontalFlip_RandomCrop_RandomPosterize",
        "uid": "27b2e4e46bbff8d103a898d59145b041"
    }
]