[
    {
        "accuracy": 0.6375,
        "batch": 64,
        "best_accuracy": 0.6389,
        "best_epoch": 7,
        "cpu_count": 24,
        "cpu_type": "x86_64",
        "cpu_usage_percent": 19.1,
        "duration": 199922934369,
        "epoch_max": 50,
        "gpu_memory_kb": 12415353.0,
        "gpu_memory_usage_percent": 0.62,
        "gpu_total_memory_kb": 24658816.0,
        "gpu_type": "NVIDIA GeForce RTX 4090",
        "gradient_norm": 39.17833766051845,
        "lr": 0.0021472255767459765,
        "lr_now": 0.0021472255767459765,
        "metric_acc": 0.6375,
        "momentum": 0.5300315091417943,
        "occupied_gpu_memory_kb": 153330.0,
        "occupied_ram_kb": 14398164.0,
        "ram_usage_percent": 44.1,
        "samples_per_second": 2024.4453959048985,
        "test_loss": 1.171463560526538,
        "total_ram_kb": 32627548.0,
        "train_accuracy": 0.77044,
        "train_loss": 0.6730749825077593,
        "transform": "bf-v1-RandomHorizontalFlip_5",
        "uid": "1e68b316e1b24572f9643dc9d9f1e9a7"
    }
]