[
    {
        "accuracy": 0.8022,
        "batch": 32,
        "best_accuracy": 0.8022,
        "best_epoch": 18,
        "cpu_count": 24,
        "cpu_type": "x86_64",
        "cpu_usage_percent": 12.8,
        "duration": 651707499498,
        "epoch_max": 50,
        "gpu_memory_kb": 2560873.0,
        "gpu_memory_usage_percent": 0.13,
        "gpu_total_memory_kb": 24696896.0,
        "gpu_type": "NVIDIA GeForce RTX 4090",
        "gradient_norm": 0.06758509485435808,
        "lr": 0.026607203482788642,
        "lr_now": 0.026607203482788642,
        "momentum": 0.6444876781004396,
        "occupied_gpu_memory_kb": 30960.0,
        "occupied_ram_kb": 11817276.0,
        "ram_usage_percent": 36.2,
        "samples_per_second": 1392.739055229486,
        "test_loss": 1.001934546298874,
        "total_ram_kb": 32620624.0,
        "train_accuracy": 0.9942,
        "train_loss": 0.019105367758640916,
        "transform": "bf-v1-RandomAdjustSharpnes_Pad_4",
        "uid": "7abc74903b4d0a6b7b30776d6bb0c7e7"
    }
]