[
    {
        "accuracy": 0.8386985248924401,
        "batch": 4,
        "best_accuracy": 0.8386985248924401,
        "best_epoch": 2,
        "dropout": 0.07406503174499734,
        "duration": 427693221600,
        "epoch_max": 5,
        "gpu_memory_kb": 2162739.0,
        "gradient_norm": 1.9604315468510297e-08,
        "lr": 8.211808003646025e-05,
        "lr_now": 8.211808003646025e-05,
        "momentum": 0.9932072288933281,
        "samples_per_second": 374.9596054499951,
        "test_loss": 0.6383176160898609,
        "train_accuracy": 0.8550172679743915,
        "train_loss": 0.5290869396000618,
        "transform": "bf-v1-RandomGrayscale_Pad_5",
        "uid": "b154de31995c8b32b350c8e4aee26ad5"
    },
    {
        "accuracy": 0.40396435156730176,
        "batch": 16,
        "best_accuracy": 0.40396435156730176,
        "best_epoch": 2,
        "dropout": 0.035695825072433685,
        "duration": 199003823390,
        "epoch_max": 5,
        "gpu_memory_kb": 691698.0,
        "gradient_norm": 2.999999653947863,
        "lr": 0.0010441909915426223,
        "lr_now": 0.0010441909915426223,
        "momentum": 0.7898206641464991,
        "samples_per_second": 707.1408945127771,
        "test_loss": 1.688517769421986,
        "train_accuracy": 0.3984738659786778,
        "train_loss": 1.6888965403807166,
        "transform": "bf-v1-RandomCrop_CenterCrop_RandomAutocontrast",
        "uid": "a2a3ea22165489db595bb58a1391659f"
    },
    {
        "accuracy": 0.1958743085433313,
        "batch": 4096,
        "best_accuracy": 0.1958743085433313,
        "best_epoch": 1,
        "dropout": 0.31547256809164775,
        "duration": 203816222284,
        "epoch_max": 5,
        "gpu_memory_kb": 2162739.0,
        "gradient_norm": 0.10642853265112684,
        "lr": 0.00784593501342702,
        "lr_now": 0.00784593501342702,
        "momentum": 0.9320457883051911,
        "samples_per_second": 705.9708991808793,
        "test_loss": 2.251910788672311,
        "train_accuracy": 0.18921058738414076,
        "train_loss": 2.257622798283895,
        "transform": "bf-v1-RandomAdjustSharpnes_Pad_4",
        "uid": "3a7fbc09c213781aeb0b268994a9560a"
    },
    {
        "accuracy": 0.1958743085433313,
        "batch": 256,
        "best_accuracy": 0.1958743085433313,
        "best_epoch": 1,
        "dropout": 0.2531573567312461,
        "duration": 1215460172307,
        "epoch_max": 5,
        "gpu_memory_kb": 2520207.0,
        "gradient_norm": 0.20420454350466097,
        "lr": 0.001724009621663299,
        "lr_now": 0.001724009621663299,
        "momentum": 0.037536889529455,
        "samples_per_second": 143.7031369662425,
        "test_loss": 2.281990196190628,
        "train_accuracy": 0.18921058738414076,
        "train_loss": 2.2840297811953447,
        "transform": "echo_299",
        "uid": "db7b4207505b15ff6abcefc2ca5a7008"
    },
    {
        "accuracy": 0.1958743085433313,
        "batch": 2,
        "best_accuracy": 0.1958743085433313,
        "best_epoch": 1,
        "dropout": 0.3729208927014832,
        "duration": 717440107712,
        "epoch_max": 5,
        "gpu_memory_kb": 2520207.0,
        "gradient_norm": 1.5366750609982465,
        "lr": 1.1664458029803913e-05,
        "lr_now": 1.1664458029803913e-05,
        "momentum": 0.46857286476362303,
        "samples_per_second": 204.39205483846752,
        "test_loss": 2.268334983735269,
        "train_accuracy": 0.18921058738414076,
        "train_loss": 2.27191111451041,
        "transform": "bf-v1-RandomAutocontrast_RandomHorizontalFlip",
        "uid": "9e5526a48d78e8e31408239791de369a"
    },
    {
        "accuracy": 0.1958743085433313,
        "batch": 128,
        "best_accuracy": 0.1958743085433313,
        "best_epoch": 1,
        "dropout": 0.3377100603010557,
        "duration": 216346785274,
        "epoch_max": 5,
        "gpu_memory_kb": 730620.5,
        "gradient_norm": 0.27489151690051106,
        "lr": 0.001781619584889023,
        "lr_now": 0.001781619584889023,
        "momentum": 0.5182814097960615,
        "samples_per_second": 673.643032559787,
        "test_loss": 2.2412185587135016,
        "train_accuracy": 0.18921058738414076,
        "train_loss": 2.248923069519522,
        "transform": "bf-v1-RandomCrop_RandomPosterize_RandomRotation",
        "uid": "3fd64ec23096549d98ca4fc1273ab8cc"
    }
]