[
    {
        "accuracy": 0.6139,
        "batch": 64,
        "best_accuracy": 0.6139,
        "best_epoch": 1,
        "cpu_count": 128,
        "cpu_type": "x86_64",
        "cpu_usage_percent": 0.9,
        "dropout": 0.39057258560239805,
        "duration": 22006254614,
        "epoch_max": 1,
        "gpu_memory_kb": 11616434.0,
        "gpu_memory_usage_percent": 7.8,
        "gpu_total_memory_kb": 24734080.0,
        "gpu_type": "NVIDIA GeForce RTX 3090",
        "gradient_norm": 2.999999632843665,
        "lr": 0.01,
        "momentum": 0.9,
        "occupied_gpu_memory_kb": 1929671.0,
        "occupied_ram_kb": 28483332.0,
        "ram_usage_percent": 12.8,
        "samples_per_second": 2272.1059733012444,
        "test_loss": 1.0862381291237606,
        "total_ram_kb": 263710532.0,
        "train_accuracy": 0.6193,
        "train_loss": 1.0671576212739091,
        "transform": "norm_32",
        "uid": "227f610890642f84de9d2b104d6d88f4"
    }
]