[
    {
        "accuracy": 0.7761,
        "batch": 4,
        "best_accuracy": 0.7761,
        "best_epoch": 7,
        "duration": 1394748729649,
        "epoch_max": 50,
        "gpu_memory_kb": 1390184.5,
        "gradient_norm": 2.004476301298845,
        "lr": 0.004913554731188214,
        "lr_now": 0.004913554731188214,
        "momentum": 0.6585165152423897,
        "samples_per_second": 229.58587108639648,
        "test_loss": 0.7038602124701254,
        "train_accuracy": 0.84124,
        "train_loss": 0.4970123524726415,
        "transform": "norm_256",
        "uid": "f5b5283af0a95980f8e6d1f3b1c36d82"
    },
    {
        "accuracy": 0.7586,
        "batch": 4,
        "best_accuracy": 0.7699,
        "best_epoch": 6,
        "cpu_count": 24,
        "cpu_type": "x86_64",
        "cpu_usage_percent": 11.0,
        "duration": 1382091756810,
        "epoch_max": 50,
        "gpu_memory_kb": 536937.0,
        "gpu_memory_usage_percent": 0.14,
        "gpu_total_memory_kb": 24696896.0,
        "gpu_type": "NVIDIA GeForce RTX 4090",
        "gradient_norm": 4.115922624888131,
        "lr": 0.004913554731188214,
        "lr_now": 0.004913554731188214,
        "momentum": 0.6585165152423897,
        "occupied_gpu_memory_kb": 35327.0,
        "occupied_ram_kb": 14006936.0,
        "ram_usage_percent": 42.9,
        "samples_per_second": 251.29184210833438,
        "test_loss": 0.7179493265064433,
        "total_ram_kb": 32620620.0,
        "train_accuracy": 0.82804,
        "train_loss": 0.5066478539079986,
        "transform": "norm_256",
        "uid": "76ff8d0fd4b24448dbeb12b2392290a9"
    }
]